<?xml version="1.0" encoding="utf-8"?>
<RegistrySettings clsid="{A3CCFC41-DFDB-43a5-8D26-0FE8B954DA51}"><Registry clsid="{9CD4B2F4-923D-47f5-A062-E897DD1DAD50}" name="Enabled" status="Enabled" image="12" changed="2025-04-29 12:39:55" uid="{6F24EDB1-2EC7-4747-92B7-14E4913CAF72}"><Properties action="U" displayDecimal="1" default="0" hive="HKEY_LOCAL_MACHINE" key="SYSTEM\CurrentControlSet\Control\SecurityProviders\SCHANNEL\Protocols\SSL 3.0\Server" name="Enabled" type="REG_DWORD" value="00000000"/></Registry>
	<Registry clsid="{9CD4B2F4-923D-47f5-A062-E897DD1DAD50}" name="DisabledByDefault" status="DisabledByDefault" image="12" changed="2025-04-29 12:39:34" uid="{0F448C2A-DA70-42BF-896A-C1914D14ABFD}"><Properties action="U" displayDecimal="1" default="0" hive="HKEY_LOCAL_MACHINE" key="SYSTEM\CurrentControlSet\Control\SecurityProviders\SCHANNEL\Protocols\SSL 3.0\Server" name="DisabledByDefault" type="REG_DWORD" value="00000001"/></Registry>
	<Registry clsid="{9CD4B2F4-923D-47f5-A062-E897DD1DAD50}" name="DisabledByDefault" status="DisabledByDefault" image="12" changed="2025-04-29 12:39:48" uid="{44E4A383-BB9D-4818-B535-7A1192809E80}"><Properties action="U" displayDecimal="1" default="0" hive="HKEY_LOCAL_MACHINE" key="SYSTEM\CurrentControlSet\Control\SecurityProviders\SCHANNEL\Protocols\SSL 3.0\Client" name="DisabledByDefault" type="REG_DWORD" value="00000001"/></Registry>
	<Registry clsid="{9CD4B2F4-923D-47f5-A062-E897DD1DAD50}" name="Enabled" status="Enabled" image="12" changed="2025-04-29 12:40:01" uid="{BE5E4968-2A68-4235-A9B4-2CFBF530313C}"><Properties action="U" displayDecimal="1" default="0" hive="HKEY_LOCAL_MACHINE" key="SYSTEM\CurrentControlSet\Control\SecurityProviders\SCHANNEL\Protocols\SSL 3.0\Client" name="Enabled" type="REG_DWORD" value="00000000"/></Registry>
	<Registry clsid="{9CD4B2F4-923D-47f5-A062-E897DD1DAD50}" name="Enabled" status="Enabled" image="12" changed="2025-04-29 12:41:47" uid="{3A9E0298-351F-4327-9F1A-D3AF6522B14F}"><Properties action="U" displayDecimal="1" default="0" hive="HKEY_LOCAL_MACHINE" key="SYSTEM\CurrentControlSet\Control\SecurityProviders\SCHANNEL\Protocols\TLS 1.0\Server" name="Enabled" type="REG_DWORD" value="00000000"/></Registry>
	<Registry clsid="{9CD4B2F4-923D-47f5-A062-E897DD1DAD50}" name="DisabledByDefault" status="DisabledByDefault" image="12" changed="2025-04-29 12:41:33" uid="{90234F65-060F-4C3E-B4A1-D920C547FDE2}"><Properties action="U" displayDecimal="1" default="0" hive="HKEY_LOCAL_MACHINE" key="SYSTEM\CurrentControlSet\Control\SecurityProviders\SCHANNEL\Protocols\TLS 1.0\Server" name="DisabledByDefault" type="REG_DWORD" value="00000001"/></Registry>
	<Registry clsid="{9CD4B2F4-923D-47f5-A062-E897DD1DAD50}" name="Enabled" status="Enabled" image="12" changed="2025-04-29 12:42:09" uid="{2DA479B0-9C7D-4EED-B005-0AF85ABC49CE}"><Properties action="U" displayDecimal="1" default="0" hive="HKEY_LOCAL_MACHINE" key="SYSTEM\CurrentControlSet\Control\SecurityProviders\SCHANNEL\Protocols\TLS 1.0\Client" name="Enabled" type="REG_DWORD" value="00000000"/></Registry>
	<Registry clsid="{9CD4B2F4-923D-47f5-A062-E897DD1DAD50}" name="DisabledByDefault" status="DisabledByDefault" image="12" changed="2025-04-29 12:42:29" uid="{A442EA22-15B5-487D-B974-FD596EA50375}"><Properties action="U" displayDecimal="1" default="0" hive="HKEY_LOCAL_MACHINE" key="SYSTEM\CurrentControlSet\Control\SecurityProviders\SCHANNEL\Protocols\TLS 1.0\Client" name="DisabledByDefault" type="REG_DWORD" value="00000001"/></Registry>
	<Registry clsid="{9CD4B2F4-923D-47f5-A062-E897DD1DAD50}" name="Enabled" status="Enabled" image="12" changed="2025-04-29 12:42:59" uid="{A64EBE85-212E-4C4F-91C9-86AB5C937173}"><Properties action="U" displayDecimal="1" default="0" hive="HKEY_LOCAL_MACHINE" key="SYSTEM\CurrentControlSet\Control\SecurityProviders\SCHANNEL\Protocols\TLS 1.1\Server" name="Enabled" type="REG_DWORD" value="00000000"/></Registry>
	<Registry clsid="{9CD4B2F4-923D-47f5-A062-E897DD1DAD50}" name="DisabledByDefault" status="DisabledByDefault" image="12" changed="2025-04-29 12:43:25" uid="{664CE555-670D-42E5-AF74-54D797B9809F}"><Properties action="U" displayDecimal="1" default="0" hive="HKEY_LOCAL_MACHINE" key="SYSTEM\CurrentControlSet\Control\SecurityProviders\SCHANNEL\Protocols\TLS 1.1\Server" name="DisabledByDefault" type="REG_DWORD" value="00000001"/></Registry>
	<Registry clsid="{9CD4B2F4-923D-47f5-A062-E897DD1DAD50}" name="Enabled" status="Enabled" image="12" changed="2025-04-29 12:43:45" uid="{00A2959C-EB2D-473F-9C09-E505C62B4900}"><Properties action="U" displayDecimal="1" default="0" hive="HKEY_LOCAL_MACHINE" key="SYSTEM\CurrentControlSet\Control\SecurityProviders\SCHANNEL\Protocols\TLS 1.1\Client" name="Enabled" type="REG_DWORD" value="00000000"/></Registry>
	<Registry clsid="{9CD4B2F4-923D-47f5-A062-E897DD1DAD50}" name="DisabledByDefault" status="DisabledByDefault" image="12" changed="2025-04-29 12:44:02" uid="{12318DD5-61A8-40F7-9C84-E0DE48C7D5A8}"><Properties action="U" displayDecimal="1" default="0" hive="HKEY_LOCAL_MACHINE" key="SYSTEM\CurrentControlSet\Control\SecurityProviders\SCHANNEL\Protocols\TLS 1.1\Client" name="DisabledByDefault" type="REG_DWORD" value="00000001"/></Registry>
</RegistrySettings>
