<BackupInst xmlns="http://www.microsoft.com/GroupPolicy/GPOOperations/Manifest"><GPOGuid><![CDATA[{A04BB3F2-732C-4E65-ADFB-04E14CF4584C}]]></GPOGuid><GPODomain><![CDATA[serval.int]]></GPODomain><GPODomainGuid><![CDATA[{510aedd4-f73a-4af5-8762-8d6a3369ae32}]]></GPODomainGuid><GPODomainController><![CDATA[ldap.serval.int]]></GPODomainController><BackupTime><![CDATA[2025-11-07T06:54:22]]></BackupTime><ID><![CDATA[{333559F0-8CEF-41B0-946E-37E280BEEFA6}]]></ID><Comment><![CDATA[]]></Comment><GPODisplayName><![CDATA[NTLM-Audit-Enabled]]></GPODisplayName></BackupInst>
